seabird_growth_rate/__init__.py
seabird_growth_rate/calculate_growth_rates.py
seabird_growth_rate/example_diversity_alpha_and_beta.py
seabird_growth_rate/hierarchical_resample.py
seabird_growth_rate/plot_log_linear_tendency.py
seabird_growth_rate-0.1.0.dist-info/LICENSE
seabird_growth_rate-0.1.0.dist-info/WHEEL
seabird_growth_rate-0.1.0.dist-info/METADATA
seabird_growth_rate-0.1.0.dist-info/RECORD
