Metadata-Version: 2.1
Name: seabird_growth_rate
Version: 0.1.0
Summary: A local Python module
Home-page: https://github.com/IslasGECI/seabird_growth_rate
Author: Ciencia de Datos • GECI
Author-email: ciencia.datos@islas.org.mx
Requires-Python: >=3.9
Classifier: License :: OSI Approved :: GNU General Public License v3 or later (GPLv3+)
